swtoolz/__init__.py
swtoolz/api.py
swtoolz-0.2.0.dist-info/LICENSE
swtoolz-0.2.0.dist-info/METADATA
swtoolz-0.2.0.dist-info/WHEEL
swtoolz-0.2.0.dist-info/top_level.txt
swtoolz-0.2.0.dist-info/RECORD
