Metadata-Version: 2.1
Name: swtoolz
Version: 0.2.0
Summary: SWToolz-Core API wrapper.
Home-page: https://github.com/MXMP/swtoolz-api-wrapper
Author: Kirill Belyaev
Author-email: bandoftoys@gmail.com
License: UNKNOWN
Platform: UNKNOWN
Classifier: Programming Language :: Python :: 3
Classifier: License :: OSI Approved :: MIT License
Classifier: Operating System :: OS Independent
Classifier: Development Status :: 3 - Alpha
Classifier: Intended Audience :: Telecommunications Industry
Classifier: Natural Language :: Russian
Requires-Dist: requests
